mafredo/__init__.py
mafredo/helpers.py
mafredo/hyddb1.py
mafredo/rao.py
mafredo-2025.4.1.dist-info/licenses/LICENSE
mafredo-2025.4.1.dist-info/METADATA
mafredo-2025.4.1.dist-info/WHEEL
mafredo-2025.4.1.dist-info/top_level.txt
mafredo-2025.4.1.dist-info/RECORD
