Metadata-Version: 2.4
Name: MaFreDo
Version: 2025.4.1
Summary: Marine Frequency Domain
Author-email: Ruben de Bruin <rubendebruin@gmail.com>
License: Mozilla Public License Version 2.0
Project-URL: Homepage, https://github.com/RubendeBruin/mafredo
Project-URL: Documentation, https://open-ocean.org/mafredo
Classifier: Development Status :: 4 - Beta
Classifier: Programming Language :: Python
Classifier: License :: OSI Approved :: Mozilla Public License 2.0 (MPL 2.0)
Requires-Python: >=3.10
License-File: LICENSE
Requires-Dist: capytaine>=2.3
Requires-Dist: matplotlib>=3.10.7
Requires-Dist: h5netcdf>=1.6.3
Requires-Dist: numpy>=2
Requires-Dist: pyyaml>=6.0.3
Requires-Dist: xarray>=2025.6.1
Dynamic: license-file
